{
  "get": {
    "summary": "CommonTeamYears",
    "operationId": "CommonTeamYears",
    "description": "[to do]",
    "security": [],
    "tags": [
      "nba"
    ],
    "parameters": [
      {
        "$ref": "../parameters/LeagueID.json"
      }
    ],
    "responses": {
      "200": {
        "description": "[to do]",
        "content": {
          "application/json": {
            "schema": {
              "type": "object",
              "properties": {
                "parameters": {
                  "type": "object",
                  "properties": {
                    "LeagueID": {
                      "$ref": "../schemas/LeagueID.json"
                    }
                  }
                },
                "resource": {
                  "const": "commonteamyears"
                },
                "resultSets": {
                  "type": "array",
                  "prefixItems": [
                    {
                      "$ref": "../data_sets/TeamYears.json"
                    }
                  ],
                  "minItems": 1,
                  "maxItems": 1
                }
              }
            }
          }
        }
      },
      "404": {
        "description": "[to do]"
      }
    }
  }
}